[
    {
      "id": "1",
      "title": "Бадриджани",
      "vendor_code": "111",
      "definition" : "",
      "price": 450,
      "img": "./Cold%20dish/Бадриджани.jpg"
    },
    {
      "id": "2",
      "title": "Лобио",
      "vendor_code": "222",
      "definition" : "",
      "price": 360,
      "img": "./Cold%20dish/Лобио.jpg"
    },
    {
      "id": "3",
      "title": "Пхали",
      "vendor_code": "333",
      "definition" : "",
      "price": 550,
      "img": "./Cold%20dish/Пхали.jpg"
    },
    {
      "id": "4",
      "title": "Хинкали",
      "vendor_code": "444e",
      "definition" : "",
      "price": 550,
      "img": "./Hot%20dish/Хинкали.jpg"
    }
    ,
    {
      "id": "5",
      "title": "Чакапули",
      "vendor_code": "4445e",
      "definition" : "",
      "price": 490,
      "img": "./Hot%20dish/Чакапули.jpg"
    },
    {
      "id": "6",
      "title": "Чашушули",
      "vendor_code": "4446e",
      "definition" : "",
      "price": 480,
      "img": "./Hot%20dish/Чашушули.jpg"
    },
    {
      "id": "7",
      "title": "Мчади",
      "vendor_code": "4447e",
      "definition" : "",
      "price": 490,
      "img": "./Bakery/Мчади.jpg"
    },
    {
      "id": "8",
      "title": "Хачапури по-аджарски",
      "vendor_code": "4448e",
      "definition" : "",
      "price": 450,
      "img": "./Bakery/Хачапури%20по-аджарски.jpg"
    },
    {
      "id": "9",
      "title": "Хачапури по-мегрельски",
      "vendor_code": "444e",
      "definition" : "",
      "price": 420,
      "img": "./Bakery/Хачапури%20по-мегрельски.jpg"
    }
    ,
    {
      "id": "10",
      "title": "Напитки",
      "vendor_code": "44410e",
      "definition" : "",
      "price": 900,
      "img": "./Bakery/drinks.jpg"
    }
  ]